central_client/__init__.py
central_client/api.py
central_client/client.py
central_client/tasks.py
coordml_runner/__init__.py
coordml_runner/cli.py
coordml_runner/config.py
coordml_runner/entry.py
coordml_runner/gpu_report.py
coordml_runner/task_runner.py
coorml_runner/__init__.py
coorml_runner/cli.py
coorml_runner/config.py
coorml_runner/entry.py
coorml_runner/gpu_report.py
coorml_runner/task_runner.py
gpu_status/__init__.py
gpu_status/gpu_status.py
coordml_runner-0.1.3.dist-info/LICENSE
coordml_runner-0.1.3.dist-info/METADATA
coordml_runner-0.1.3.dist-info/WHEEL
coordml_runner-0.1.3.dist-info/entry_points.txt
coordml_runner-0.1.3.dist-info/top_level.txt
coordml_runner-0.1.3.dist-info/RECORD
