Metadata-Version: 2.1
Name: coordml-runner
Version: 0.1.3
Summary: Python CoordML Runner
Home-page: https://github.com/coordml/runner
Author: Yichen Xu
Author-email: yichen.xu@monad.email
License: UNKNOWN
Platform: UNKNOWN
Classifier: Programming Language :: Python :: 3
Classifier: License :: OSI Approved :: MIT License
Classifier: Operating System :: OS Independent
Requires-Python: >=3.7
Requires-Dist: aiohttp
Requires-Dist: pyyaml
Requires-Dist: parse
Requires-Dist: gpustat
